turkish_syllable/__init__.py
turkish_syllable/csyllable_tr.py
turkish_syllable/libsyllable.cpython-39-x86_64-linux-gnu.so
turkish_syllable/syllable.c
turkish_syllable-0.2.33.dist-info/METADATA
turkish_syllable-0.2.33.dist-info/WHEEL
turkish_syllable-0.2.33.dist-info/top_level.txt
turkish_syllable-0.2.33.dist-info/RECORD
turkish_syllable-0.2.33.dist-info/licenses/LICENSE
