Metadata-Version: 2.4
Name: turkish-syllable
Version: 0.2.33
Summary: A Turkish syllable splitter implemented in C with Python bindings
Author-email: Ahmet Ozdemir <ahmetozdemiir.ao@gmail.com>
License: MIT License
Project-URL: Homepage, https://github.com/ahmetozdemirrr/Turkish-Syllable
Project-URL: Issues, https://github.com/ahmetozdemirrr/Turkish-Syllable/issues
Classifier: Programming Language :: Python :: 3
Classifier: Programming Language :: C
Classifier: Operating System :: OS Independent
Classifier: Development Status :: 4 - Beta
Classifier: Intended Audience :: Developers
Classifier: Topic :: Text Processing :: Linguistic
Classifier: License :: OSI Approved :: MIT License
Requires-Python: >=3.9
License-File: LICENSE
Dynamic: license-file
